polars_geodates-0.19.12.dist-info/METADATA
polars_geodates-0.19.12.dist-info/WHEEL
polars_geodates-0.19.12.dist-info/license_files/LICENSE
_internal/__init__.py
_internal/_internal.cpython-37m-x86_64-linux-gnu.so
polars_geodates-0.19.12.dist-info/RECORD
