Metadata-Version: 2.3
Name: polars_geodates
Version: 0.19.12
Classifier: Programming Language :: Rust
Classifier: Programming Language :: Python :: Implementation :: CPython
Classifier: Programming Language :: Python :: Implementation :: PyPy
License-File: LICENSE
Summary: Converts from onetime to another based on latatitude and longitude
Author: Hugo Pendlebury
Requires-Python: >=3.8
